client/__init__.py
client/logger.py
client/prompt.py
fastrepl_client-0.0.1.dist-info/METADATA
fastrepl_client-0.0.1.dist-info/WHEEL
fastrepl_client-0.0.1.dist-info/RECORD
