Metadata-Version: 2.1
Name: fastrepl-client
Version: 0.0.1
Summary: 
Author: yujonglee
Author-email: yujonglee@repllabs.ai
Requires-Python: >=3.9,<3.12
Classifier: Programming Language :: Python :: 3
Classifier: Programming Language :: Python :: 3.9
Classifier: Programming Language :: Python :: 3.10
Classifier: Programming Language :: Python :: 3.11
Requires-Dist: httpx (>=0.25.0,<0.26.0)
Requires-Dist: jinja2 (>=3.1.2,<4.0.0)
Requires-Dist: litellm (>=0.4.0,<0.5.0)
